{
  "version": "0.2",
  "language": "en",
  "ignorePaths": [
    "**/node_modules/**",
    "**/build/**",
    "**/dist/**",
    "**/OLD/**",
    "**/.yarn/**",
    "**/.next/**",
    "**/cdk.out/**",
    "cdk.context.json",
    "yarn-error.log",
    "**/tsconfig*",
    "Dockerfile",
    "cdk.json"
  ],
  "words": [
    "ABCDEFGHJKMNPQRSTUVWXYZ",
    "allcontributors",
    "barebones",
    "cacheable",
    "cellspacing",
    "certificatemanager",
    "Codereview",
    "consts",
    "Cooldown",
    "deregistration",
    "devs",
    "embla",
    "fargate",
    "heroicons",
    "joswayski",
    "ksuid",
    "lspace",
    "mantine",
    "mazupicua",
    "noopener",
    "nprogress",
    "nrwl",
    "Plutomi",
    "plutomiinc",
    "praguru",
    "roadmap",
    "rspace",
    "shipit",
    "signup",
    "signups",
    "stylis",
    "tabler",
    "tanstack",
    "timesheets",
    "tiptap",
    "TLDR",
    "TOTP",
    "totps",
    "trenchard",
    "Usergroup",
    "Valerio",
    "valign",
    "Vcard",
    "wafv2",
    "waitlist",
    "Wpforms",
    "zustand"
  ],
  "overrides": []
}
